ask/__init__.py
ask/config.py
ask/exceptions.py
ask/main.py
ask/providers/__init__.py
ask/providers/anthropic.py
ask/providers/base.py
ask/providers/gemini.py
ask/providers/openai.py
terminal_sherpa-0.2.0.dist-info/licenses/LICENSE
test/conftest.py
test/test_anthropic.py
test/test_config.py
test/test_exceptions.py
test/test_gemini.py
test/test_main.py
test/test_openai.py
test/test_providers.py
terminal_sherpa-0.2.0.dist-info/METADATA
terminal_sherpa-0.2.0.dist-info/WHEEL
terminal_sherpa-0.2.0.dist-info/entry_points.txt
terminal_sherpa-0.2.0.dist-info/top_level.txt
terminal_sherpa-0.2.0.dist-info/RECORD
