Metadata-Version: 2.4
Name: terminal-sherpa
Version: 0.2.0
Summary: AI-powered bash command generator
Requires-Python: >=3.13
License-File: LICENSE
Requires-Dist: anthropic>=0.7.0
Requires-Dist: black>=25.1.0
Requires-Dist: cosmic-ray>=8.3.4
Requires-Dist: google-genai>=1.26.0
Requires-Dist: loguru>=0.7.0
Requires-Dist: mutatest>=3.1.0
Requires-Dist: openai>=1.0.0
Requires-Dist: pytest>=8.0.0
Requires-Dist: pytest-cov>=4.0.0
Requires-Dist: pytest-mock>=3.12.0
Requires-Dist: ruff>=0.12.3
Requires-Dist: setuptools>=80.9.0
Requires-Dist: taskipy>=1.14.1
Requires-Dist: toml>=0.10.0
Dynamic: license-file
